vault/__init__.py
vault/client.py
vault_talenttech_oss-1.1.0.dist-info/LICENSE.txt
vault_talenttech_oss-1.1.0.dist-info/METADATA
vault_talenttech_oss-1.1.0.dist-info/WHEEL
vault_talenttech_oss-1.1.0.dist-info/top_level.txt
vault_talenttech_oss-1.1.0.dist-info/RECORD
