Metadata-Version: 2.1
Name: vault-talenttech-oss
Version: 1.1.0
Summary: TopMind Vault Client Helper
Home-page: https://github.com/severgroup-tt/topmind-commons
Author: Pavel Popov
Author-email: p.popov@talenttech.ru
License: MIT
Platform: UNKNOWN
Classifier: Programming Language :: Python :: 3
Classifier: License :: OSI Approved :: MIT License
Classifier: Operating System :: OS Independent
Requires-Python: >=3.6
Requires-Dist: hvac
